{
  "db_name": "PostgreSQL",
  "query": "SELECT path FROM artifacts\n        WHERE repository_id = $1 AND path LIKE '%/' || $2 ESCAPE '\\' AND is_deleted = false\n        LIMIT 1",
  "describe": {
    "columns": [
      {
        "ordinal": 0,
        "name": "path",
        "type_info": "Varchar"
      }
    ],
    "parameters": {
      "Left": [
        "Uuid",
        "Text"
      ]
    },
    "nullable": [
      false
    ]
  },
  "hash": "66b8c81ce4c0097c7bd855193ce3ed4a3651488a4687b7bc7e2423946c5a954d"
}
